{"nodes": [{"id": "c_projetos_condominios_scripts_cleanup_data_py", "label": "cleanup_data.py", "file_type": "code", "source_file": "C:\\projetos\\condominios\\scripts\\cleanup_data.py", "source_location": "L1"}], "edges": [{"source": "c_projetos_condominios_scripts_cleanup_data_py", "target": "os", "relation": "imports", "context": "import", "confidence": "EXTRACTED", "source_file": "C:\\projetos\\condominios\\scripts\\cleanup_data.py", "source_location": "L1", "weight": 1.0}, {"source": "c_projetos_condominios_scripts_cleanup_data_py", "target": "sys", "relation": "imports", "context": "import", "confidence": "EXTRACTED", "source_file": "C:\\projetos\\condominios\\scripts\\cleanup_data.py", "source_location": "L2", "weight": 1.0}, {"source": "c_projetos_condominios_scripts_cleanup_data_py", "target": "dotenv", "relation": "imports_from", "context": "import", "confidence": "EXTRACTED", "source_file": "C:\\projetos\\condominios\\scripts\\cleanup_data.py", "source_location": "L3", "weight": 1.0}, {"source": "c_projetos_condominios_scripts_cleanup_data_py", "target": "supabase", "relation": "imports_from", "context": "import", "confidence": "EXTRACTED", "source_file": "C:\\projetos\\condominios\\scripts\\cleanup_data.py", "source_location": "L4", "weight": 1.0}], "raw_calls": []}